FuzzySystem/__init__.py
FuzzySystem/config.py
FuzzySystem/defuzzifier.py
FuzzySystem/fis.py
FuzzySystem/fuzzy_operations.py
FuzzySystem/fuzzyrule.py
FuzzySystem/fuzzyset.py
FuzzySystem/fuzzyvariable.py
FuzzySystem/matlab_importer.py
FuzzySystem/membership_function.py
FuzzySystem/nonsingleton.py
FuzzySystem/output.py
FuzzySystem/utils.py
FuzzySystem-0.242.dist-info/METADATA
FuzzySystem-0.242.dist-info/WHEEL
FuzzySystem-0.242.dist-info/top_level.txt
FuzzySystem-0.242.dist-info/RECORD
