Metadata-Version: 2.1
Name: FuzzySystem
Version: 0.242
Summary: FIS Framework
Home-page: https://github.com/Raul-Navarro/fuzzy-framework
Author: Raul Navarro-Almanza
Author-email: rnavarro@uabc.edu.mx
License: MIT
Platform: UNKNOWN
Requires-Dist: numpy
Requires-Dist: matplotlib
Requires-Dist: pandas
